bruteloops/__init__.py
bruteloops/args.py
bruteloops/brute.py
bruteloops/brute_time.py
bruteloops/db_manager.py
bruteloops/enums.py
bruteloops/errors.py
bruteloops/jitter.py
bruteloops/logging.py
bruteloops/models.py
bruteloops/queries.py
bruteloops/sql.py
tests/__init__.py
tests/conftest.py
tests/test_args.py
tests/test_breakers.py
tests/test_config.py
tests/test_db_manager.py
tests/test_import.py
bruteloops-1.0.1.dist-info/LICENSE
bruteloops-1.0.1.dist-info/METADATA
bruteloops-1.0.1.dist-info/WHEEL
bruteloops-1.0.1.dist-info/top_level.txt
bruteloops-1.0.1.dist-info/RECORD
