Metadata-Version: 2.1
Name: bruteloops
Version: 1.0.1
Summary: A password guessing API.
Home-page: https://github.com/arch4ngel/bruteloops
Author: Justin Angel
Author-email: justin@arch4ngel.ninja
Classifier: Programming Language :: Python :: 3
Classifier: License :: OSI Approved :: MIT License
Classifier: Operating System :: POSIX :: Linux
Requires-Python: >=3.9
License-File: LICENSE
Requires-Dist: sqlalchemy (==1.4.0)
Requires-Dist: billiard (>=3.6.3.0)
Requires-Dist: pydantic
